<?xml version="1.0" encoding="utf-8"?>
<data>
  <DataType Name="Data Types0" BaseType="" ArrayType="" Length="" InitialValue="" EnumValue="" Comment="" OffsetChannel="" OffsetBit="" IsControllerDefinedType="false" Order="0" OffsetType="">
    <DataType Name="FLASHLAMP" BaseType="STRUCT" ArrayType="" Length="" InitialValue="" EnumValue="" Comment="" OffsetChannel="" OffsetBit="" IsControllerDefinedType="false" Order="14" OffsetType="" Id="dccee5c4-642c-4935-be69-8e3ab854ca87">
      <DataType Name="Cfg" BaseType="OBJ\Flashlamp_Config" ArrayType="" Length="" InitialValue="" EnumValue="" Comment="Config -" OffsetChannel="" OffsetBit="" IsControllerDefinedType="false" Order="0" OffsetType="" Id="0e75c0a0-c02c-458c-b8d0-386defd03315" />
      <DataType Name="Cmd" BaseType="OBJ\Flashlamp_Command" ArrayType="" Length="" InitialValue="" EnumValue="" Comment="Command -" OffsetChannel="" OffsetBit="" IsControllerDefinedType="false" Order="0" OffsetType="" Id="31b46291-2cd6-4292-a798-c3f4d1f76e1c" />
      <DataType Name="Sta" BaseType="OBJ\Flashlamp_Status" ArrayType="" Length="" InitialValue="" EnumValue="" Comment="Status -" OffsetChannel="" OffsetBit="" IsControllerDefinedType="false" Order="0" OffsetType="" Id="4b3be8bc-ac34-4df0-b303-1ed5dc27499f" />
      <DataType Name="Xch" BaseType="OBJ\Flashlamp_Exchange" ArrayType="" Length="" InitialValue="" EnumValue="" Comment="Private -" OffsetChannel="" OffsetBit="" IsControllerDefinedType="false" Order="0" OffsetType="" Id="50046dac-75d1-4069-8c60-9f4d124b6a3e" />
    </DataType>
    <DataType Name="Flashlamp_Config" BaseType="STRUCT" ArrayType="" Length="" InitialValue="" EnumValue="" Comment="" OffsetChannel="" OffsetBit="" IsControllerDefinedType="false" Order="11" OffsetType="" Id="c33ca625-2fd6-4430-9745-35c455d9213f">
      <DataType Name="IsSchneider" BaseType="Boolean" ArrayType="" Length="" InitialValue="" EnumValue="" Comment="" OffsetChannel="" OffsetBit="" IsControllerDefinedType="false" Order="0" OffsetType="" Id="7577e7c9-78dc-46a1-b20d-ee23186e2684" />
      <DataType Name="IsBalluf" BaseType="Boolean" ArrayType="" Length="" InitialValue="" EnumValue="" Comment="" OffsetChannel="" OffsetBit="" IsControllerDefinedType="false" Order="0" OffsetType="" Id="232529fe-1c73-4527-a1b1-cdc7c34b8987" />
      <DataType Name="IsRGB" BaseType="Boolean" ArrayType="" Length="" InitialValue="" EnumValue="" Comment="" OffsetChannel="" OffsetBit="" IsControllerDefinedType="false" Order="0" OffsetType="" Id="f3bfbe04-b7b4-4657-8b33-faaa0d41af73" />
      <DataType Name="IsMurr" BaseType="Boolean" ArrayType="" Length="" InitialValue="" EnumValue="" Comment="" OffsetChannel="" OffsetBit="" IsControllerDefinedType="false" Order="0" OffsetType="" Id="5b6642fe-0041-478e-9328-940bdda97ae1" />
    </DataType>
    <DataType Name="Flashlamp_Command" BaseType="STRUCT" ArrayType="" Length="" InitialValue="" EnumValue="" Comment="" OffsetChannel="" OffsetBit="" IsControllerDefinedType="false" Order="10" OffsetType="" Id="770730a5-f53c-4b62-b394-5aebec7b987d">
      <DataType Name="Color" BaseType="OBJ\eColor" ArrayType="" Length="" InitialValue="" EnumValue="" Comment="Chose the color of the light" OffsetChannel="" OffsetBit="" IsControllerDefinedType="false" Order="0" OffsetType="" Id="43d0e982-997d-44bf-8bff-c81e76bc9e41" />
      <DataType Name="Effect" BaseType="OBJ\eEffect" ArrayType="" Length="" InitialValue="" EnumValue="" Comment="Chose the status of the light" OffsetChannel="" OffsetBit="" IsControllerDefinedType="false" Order="0" OffsetType="" Id="dbe41904-6ed2-496b-8ee9-eef73203405c" />
      <DataType Name="Progress" BaseType="Single" ArrayType="" Length="" InitialValue="" EnumValue="" Comment="Define level in filling mode [0..100%]" OffsetChannel="" OffsetBit="" IsControllerDefinedType="false" Order="0" OffsetType="" Id="5813d59a-2b38-4429-8ba6-dcd450521453" />
    </DataType>
    <DataType Name="Flashlamp_Status" BaseType="STRUCT" ArrayType="" Length="" InitialValue="" EnumValue="" Comment="" OffsetChannel="" OffsetBit="" IsControllerDefinedType="false" Order="9" OffsetType="" Id="5633027f-9837-4d90-9a15-4ab989e5ef4d">
      <DataType Name="Enabled" BaseType="Boolean" ArrayType="" Length="" InitialValue="" EnumValue="" Comment="Flash lamp is used" OffsetChannel="" OffsetBit="" IsControllerDefinedType="false" Order="0" OffsetType="" Id="7f19e16e-2a4b-40db-bdc1-c763b3c6b782" />
      <DataType Name="Ready" BaseType="Boolean" ArrayType="" Length="" InitialValue="" EnumValue="" Comment="Flash lamp is ready to work" OffsetChannel="" OffsetBit="" IsControllerDefinedType="false" Order="0" OffsetType="" Id="5f30233b-fd2e-47c2-bd6f-e9c11c874ee4" />
      <DataType Name="Fault" BaseType="Boolean" ArrayType="" Length="" InitialValue="" EnumValue="" Comment="Flash lamp can't display the command" OffsetChannel="" OffsetBit="" IsControllerDefinedType="false" Order="0" OffsetType="" Id="98990590-e7ac-40d0-8bce-48363978c478" />
      <DataType Name="Commissioning" BaseType="Boolean" ArrayType="" Length="" InitialValue="" EnumValue="" Comment="Flash lamp is in commissioning mode" OffsetChannel="" OffsetBit="" IsControllerDefinedType="false" Order="0" OffsetType="" Id="85cbd530-ab67-4975-86ee-9268f743e9e9" />
      <DataType Name="LevelMode" BaseType="Boolean" ArrayType="" Length="" InitialValue="" EnumValue="" Comment="Flash lamp is in level mode" OffsetChannel="" OffsetBit="" IsControllerDefinedType="false" Order="0" OffsetType="" Id="4403635a-6df9-4e96-a0c1-f0eb012f983f" />
    </DataType>
    <DataType Name="Flashlamp_Exchange" BaseType="STRUCT" ArrayType="" Length="" InitialValue="" EnumValue="" Comment="" OffsetChannel="" OffsetBit="" IsControllerDefinedType="false" Order="8" OffsetType="" Id="719b1856-8f06-4d25-b512-b255f1174b15">
      <DataType Name="Rank" BaseType="Byte" ArrayType="" Length="" InitialValue="" EnumValue="" Comment="Current priority level (Priority on low number)" OffsetChannel="" OffsetBit="" IsControllerDefinedType="false" Order="0" OffsetType="" Id="ffb883e1-74e9-4ae2-8894-fabc8092ebc5" />
    </DataType>
    <DataType Name="PNEUMATIC" BaseType="STRUCT" ArrayType="" Length="" InitialValue="" EnumValue="" Comment="" OffsetChannel="" OffsetBit="" IsControllerDefinedType="false" Order="13" OffsetType="" Id="c88a7762-7b80-40ca-9d90-666b5ca5b280">
      <DataType Name="Cfg" BaseType="OBJ\Pneumatic_Config" ArrayType="" Length="" InitialValue="" EnumValue="" Comment="Config -" OffsetChannel="" OffsetBit="" IsControllerDefinedType="false" Order="0" OffsetType="" Id="3d4fbba8-9a95-446c-8764-0131bc05d7a9" />
      <DataType Name="Cmd" BaseType="OBJ\Pneumatic_Command" ArrayType="" Length="" InitialValue="" EnumValue="" Comment="Command -" OffsetChannel="" OffsetBit="" IsControllerDefinedType="false" Order="0" OffsetType="" Id="af937850-4a25-4ac6-84a6-c693680f0c45" />
      <DataType Name="Sta" BaseType="OBJ\Pneumatic_Status" ArrayType="" Length="" InitialValue="" EnumValue="" Comment="Status -" OffsetChannel="" OffsetBit="" IsControllerDefinedType="false" Order="0" OffsetType="" Id="2f6ee3cc-3d72-4713-9a7d-62aa534aa6cd" />
      <DataType Name="Msg" BaseType="OBJ\Pneumatic_Message" ArrayType="" Length="" InitialValue="" EnumValue="" Comment="Alarms -" OffsetChannel="" OffsetBit="" IsControllerDefinedType="false" Order="0" OffsetType="" Id="27312e99-93cd-4402-8f11-81d1a63e2b6d" />
    </DataType>
    <DataType Name="Pneumatic_Config" BaseType="STRUCT" ArrayType="" Length="" InitialValue="" EnumValue="" Comment="" OffsetChannel="" OffsetBit="" IsControllerDefinedType="false" Order="7" OffsetType="" Id="d832885f-8e82-49fa-b842-a7dc9f5e4c9f">
      <DataType Name="Done" BaseType="Boolean" ArrayType="" Length="" InitialValue="" EnumValue="" Comment="Configuration is done" OffsetChannel="" OffsetBit="" IsControllerDefinedType="false" Order="0" OffsetType="" Id="27902c93-b171-4534-922c-fc4493961705" />
      <DataType Name="SingleActing" BaseType="Boolean" ArrayType="" Length="" InitialValue="" EnumValue="" Comment="Single-acting cylinders with one input to go OUT, and a spring to return IN" OffsetChannel="" OffsetBit="" IsControllerDefinedType="false" Order="0" OffsetType="" Id="0776f2e0-129b-400c-a1fe-eba5befde91c" />
      <DataType Name="DoubleActing" BaseType="Boolean" ArrayType="" Length="" InitialValue="" EnumValue="" Comment="Double-acting cylinders use the force of air to move" OffsetChannel="" OffsetBit="" IsControllerDefinedType="false" Order="0" OffsetType="" Id="89fdbf04-f1d7-415d-b68a-14fc95c63ce0" />
      <DataType Name="AsSensorOut" BaseType="Boolean" ArrayType="" Length="" InitialValue="" EnumValue="" Comment="Cylinder is equiped with OUT position sensor" OffsetChannel="" OffsetBit="" IsControllerDefinedType="false" Order="0" OffsetType="" Id="be7260c1-38f3-4316-bb2b-0f37fd59cb0a" />
      <DataType Name="AsSensorIn" BaseType="Boolean" ArrayType="" Length="" InitialValue="" EnumValue="" Comment="Cylinder is equiped with IN position sensor" OffsetChannel="" OffsetBit="" IsControllerDefinedType="false" Order="0" OffsetType="" Id="50c73c48-3770-4311-8142-fa7c481efda7" />
      <DataType Name="OrderByFlank" BaseType="Boolean" ArrayType="" Length="" InitialValue="" EnumValue="" Comment="Order is given by &quot;flank&quot;" OffsetChannel="" OffsetBit="" IsControllerDefinedType="false" Order="0" OffsetType="" Id="c4f6f347-0c5a-4b31-820e-2dd502269b25" />
      <DataType Name="OrderByCoil" BaseType="Boolean" ArrayType="" Length="" InitialValue="" EnumValue="" Comment="Order is given by &quot;coil&quot;" OffsetChannel="" OffsetBit="" IsControllerDefinedType="false" Order="0" OffsetType="" Id="3f89e1df-0e6b-4e5f-96a4-1315d6afa0b7" />
    </DataType>
    <DataType Name="Pneumatic_Command" BaseType="STRUCT" ArrayType="" Length="" InitialValue="" EnumValue="" Comment="" OffsetChannel="" OffsetBit="" IsControllerDefinedType="false" Order="6" OffsetType="" Id="aa6ca7d8-61b7-456e-b494-a47a74ee4e5f">
      <DataType Name="GoIn" BaseType="Boolean" ArrayType="" Length="" InitialValue="" EnumValue="" Comment="&quot;Flank&quot; order to go IN" OffsetChannel="" OffsetBit="" IsControllerDefinedType="false" Order="0" OffsetType="" Id="c73cbf03-b16a-4a37-9cf1-7fecbe6cec39" />
      <DataType Name="GoOut" BaseType="Boolean" ArrayType="" Length="" InitialValue="" EnumValue="" Comment="&quot;Flank&quot; order to go OUT" OffsetChannel="" OffsetBit="" IsControllerDefinedType="false" Order="0" OffsetType="" Id="f9dfd422-6a25-4190-aec6-1e17000159fa" />
      <DataType Name="Output" BaseType="Boolean" ArrayType="" Length="" InitialValue="" EnumValue="" Comment="&quot;Coil&quot; order. If coil is OFF, cylinder is inside, if ON, cylinder is outside" OffsetChannel="" OffsetBit="" IsControllerDefinedType="false" Order="0" OffsetType="" Id="c713c2ca-0925-41b4-a411-a4e7e2aadc13" />
      <DataType Name="Interlock_In" BaseType="Boolean" ArrayType="" Length="" InitialValue="" EnumValue="" Comment="Interlock IN movement" OffsetChannel="" OffsetBit="" IsControllerDefinedType="false" Order="0" OffsetType="" Id="96b11f59-0b94-4e42-beaa-3394784a0e22" />
      <DataType Name="Interlock_Out" BaseType="Boolean" ArrayType="" Length="" InitialValue="" EnumValue="" Comment="Interlock OUT movement" OffsetChannel="" OffsetBit="" IsControllerDefinedType="false" Order="0" OffsetType="" Id="44994887-65c3-4e0c-8116-451a90a1a914" />
    </DataType>
    <DataType Name="Pneumatic_Status" BaseType="STRUCT" ArrayType="" Length="" InitialValue="" EnumValue="" Comment="" OffsetChannel="" OffsetBit="" IsControllerDefinedType="false" Order="5" OffsetType="" Id="8a79612f-29f7-42b2-947b-2c7e45c0c3ed">
      <DataType Name="Enabled" BaseType="Boolean" ArrayType="" Length="" InitialValue="" EnumValue="" Comment="Cylinder is used" OffsetChannel="" OffsetBit="" IsControllerDefinedType="false" Order="0" OffsetType="" Id="6ea49a4d-2c46-432e-a3ca-f27e71fe4440" />
      <DataType Name="Ready" BaseType="Boolean" ArrayType="" Length="" InitialValue="" EnumValue="" Comment="Cylinder is ready to work" OffsetChannel="" OffsetBit="" IsControllerDefinedType="false" Order="0" OffsetType="" Id="ed85ca28-fc0f-4284-9d56-35d4a9cf6657" />
      <DataType Name="IsOut" BaseType="Boolean" ArrayType="" Length="" InitialValue="" EnumValue="" Comment="Cylinder is OUT" OffsetChannel="" OffsetBit="" IsControllerDefinedType="false" Order="0" OffsetType="" Id="345a477c-a10c-49ea-a01b-6f392fd55783" />
      <DataType Name="IsIn" BaseType="Boolean" ArrayType="" Length="" InitialValue="" EnumValue="" Comment="Cylinder is IN" OffsetChannel="" OffsetBit="" IsControllerDefinedType="false" Order="0" OffsetType="" Id="1ec254e7-f68c-47ac-8109-5f01662625ab" />
      <DataType Name="Fault" BaseType="Boolean" ArrayType="" Length="" InitialValue="" EnumValue="" Comment="Cylinder in fault" OffsetChannel="" OffsetBit="" IsControllerDefinedType="false" Order="0" OffsetType="" Id="67a66c91-07db-4309-a10a-3d5868ce90e6" />
      <DataType Name="SensorOut" BaseType="Boolean" ArrayType="" Length="" InitialValue="" EnumValue="" Comment="Sensor feedback for cylinder is in position OUT" OffsetChannel="" OffsetBit="" IsControllerDefinedType="false" Order="0" OffsetType="" Id="41b56ee2-6711-4a64-954f-f77f676cd432" />
      <DataType Name="SensorIn" BaseType="Boolean" ArrayType="" Length="" InitialValue="" EnumValue="" Comment="Sensor feedback for cylinder is in position IN" OffsetChannel="" OffsetBit="" IsControllerDefinedType="false" Order="0" OffsetType="" Id="d2c3b8e4-a27c-4373-a028-3fdec3d961c8" />
      <DataType Name="Commissioning" BaseType="Boolean" ArrayType="" Length="" InitialValue="" EnumValue="" Comment="Cylinder is in commissioning mode" OffsetChannel="" OffsetBit="" IsControllerDefinedType="false" Order="0" OffsetType="" Id="1e5bc503-ca36-43cc-8715-86947dc0bfe0" />
      <DataType Name="MovingIn" BaseType="Boolean" ArrayType="" Length="" InitialValue="" EnumValue="" Comment="Cylinder is moving IN" OffsetChannel="" OffsetBit="" IsControllerDefinedType="false" Order="0" OffsetType="" Id="ae03e91e-2f25-4eea-9410-52e96fbbc3cd" />
      <DataType Name="MovingOut" BaseType="Boolean" ArrayType="" Length="" InitialValue="" EnumValue="" Comment="Cylinder is moving OUT" OffsetChannel="" OffsetBit="" IsControllerDefinedType="false" Order="0" OffsetType="" Id="5f215f7d-67cd-4541-9bd7-9a9b32edd329" />
      <DataType Name="Interlocked_In" BaseType="Boolean" ArrayType="" Length="" InitialValue="" EnumValue="" Comment="Movement IN are interlocked" OffsetChannel="" OffsetBit="" IsControllerDefinedType="false" Order="0" OffsetType="" Id="ea4d1238-fab6-4f29-a14f-3b9f651a029d" />
      <DataType Name="Interlocked_Out" BaseType="Boolean" ArrayType="" Length="" InitialValue="" EnumValue="" Comment="Movement OUT are interlocked" OffsetChannel="" OffsetBit="" IsControllerDefinedType="false" Order="0" OffsetType="" Id="8b3f4cf1-1329-41ce-874c-40707f252478" />
    </DataType>
    <DataType Name="Pneumatic_Message" BaseType="STRUCT" ArrayType="" Length="" InitialValue="" EnumValue="" Comment="" OffsetChannel="" OffsetBit="" IsControllerDefinedType="false" Order="4" OffsetType="" Id="f51445a8-75b6-4475-abd5-f18aa4e97ac0">
      <DataType Name="MultiOrder" BaseType="Boolean" ArrayType="" Length="" InitialValue="" EnumValue="" Comment="Cylinder recive &quot;Flank&quot; and &quot;Coil&quot; order " OffsetChannel="" OffsetBit="" IsControllerDefinedType="false" Order="0" OffsetType="" Id="6969c7ec-2122-452b-ac0b-6bdac0264ad7" />
      <DataType Name="TimeoutGoIn" BaseType="Boolean" ArrayType="" Length="" InitialValue="" EnumValue="" Comment="Cylinder spend too much time to go in IN position" OffsetChannel="" OffsetBit="" IsControllerDefinedType="false" Order="0" OffsetType="" Id="0c57ea5f-31fd-4d2b-a79e-337e4ede17df" />
      <DataType Name="TimeoutGoOut" BaseType="Boolean" ArrayType="" Length="" InitialValue="" EnumValue="" Comment="Cylinder spend too much time to go in OUT position" OffsetChannel="" OffsetBit="" IsControllerDefinedType="false" Order="0" OffsetType="" Id="475efcfe-97b3-40dd-8703-491ea0286477" />
      <DataType Name="TooMuchConfig" BaseType="Boolean" ArrayType="" Length="" InitialValue="" EnumValue="" Comment="Cylinder has more than one configuration bloc" OffsetChannel="" OffsetBit="" IsControllerDefinedType="false" Order="0" OffsetType="" Id="a34d0778-965f-41aa-b43e-886042a19995" />
    </DataType>
    <DataType Name="eColor" BaseType="ENUM" ArrayType="" Length="" InitialValue="" EnumValue="" Comment="Color selection" OffsetChannel="" OffsetBit="" IsControllerDefinedType="false" Order="0" OffsetType="" Id="e517fadd-38b0-46f9-8721-9ba27b00a4de">
      <DataType Name="NoColor" BaseType="DINT" ArrayType="" Length="" InitialValue="" EnumValue="0" Comment="Off" OffsetChannel="" OffsetBit="" IsControllerDefinedType="false" Order="0" OffsetType="" Id="f944e7ef-3abf-4946-9d4f-a68a9184b755" />
      <DataType Name="Red" BaseType="DINT" ArrayType="" Length="" InitialValue="" EnumValue="1" Comment="Red" OffsetChannel="" OffsetBit="" IsControllerDefinedType="false" Order="0" OffsetType="" Id="2d606c54-752c-4d04-962f-51efb34bafe5" />
      <DataType Name="Lime" BaseType="DINT" ArrayType="" Length="" InitialValue="" EnumValue="2" Comment="Lime" OffsetChannel="" OffsetBit="" IsControllerDefinedType="false" Order="0" OffsetType="" Id="946314ad-9fab-47f3-ab53-44c609302c92" />
      <DataType Name="Yellow" BaseType="DINT" ArrayType="" Length="" InitialValue="" EnumValue="3" Comment="Yellow" OffsetChannel="" OffsetBit="" IsControllerDefinedType="false" Order="0" OffsetType="" Id="7a1e77bb-c725-4f43-a959-d5b108e2590d" />
      <DataType Name="Blue" BaseType="DINT" ArrayType="" Length="" InitialValue="" EnumValue="4" Comment="Blue" OffsetChannel="" OffsetBit="" IsControllerDefinedType="false" Order="0" OffsetType="" Id="3d879c13-e608-4e81-9c5f-f4839d2e519d" />
      <DataType Name="Fuchsia" BaseType="DINT" ArrayType="" Length="" InitialValue="" EnumValue="5" Comment="Fuchsia" OffsetChannel="" OffsetBit="" IsControllerDefinedType="false" Order="0" OffsetType="" Id="2782f833-e322-417d-a7d2-300937e1b620" />
      <DataType Name="Aqua" BaseType="DINT" ArrayType="" Length="" InitialValue="" EnumValue="6" Comment="Aqua" OffsetChannel="" OffsetBit="" IsControllerDefinedType="false" Order="0" OffsetType="" Id="1a078f66-9b51-4bf5-943f-d91244840f1d" />
      <DataType Name="White" BaseType="DINT" ArrayType="" Length="" InitialValue="" EnumValue="7" Comment="White" OffsetChannel="" OffsetBit="" IsControllerDefinedType="false" Order="0" OffsetType="" Id="a522f559-cc27-4a17-b839-08d975c01630" />
      <DataType Name="Black" BaseType="DINT" ArrayType="" Length="" InitialValue="" EnumValue="8" Comment="Black" OffsetChannel="" OffsetBit="" IsControllerDefinedType="false" Order="0" OffsetType="" Id="11ef698b-ad16-45c9-a935-9af1ba7c745f" />
      <DataType Name="Brown" BaseType="DINT" ArrayType="" Length="" InitialValue="" EnumValue="9" Comment="Brown (Dark red)" OffsetChannel="" OffsetBit="" IsControllerDefinedType="false" Order="0" OffsetType="" Id="9769df2a-cba2-4bc1-9cac-e6190572cdd8" />
      <DataType Name="Green" BaseType="DINT" ArrayType="" Length="" InitialValue="" EnumValue="10" Comment="Green (Dark lime)" OffsetChannel="" OffsetBit="" IsControllerDefinedType="false" Order="0" OffsetType="" Id="bd605489-843c-47ec-b0bb-19ad8b58041f" />
      <DataType Name="Orange" BaseType="DINT" ArrayType="" Length="" InitialValue="" EnumValue="11" Comment="Orange (Dark yellow)" OffsetChannel="" OffsetBit="" IsControllerDefinedType="false" Order="0" OffsetType="" Id="0a383fdc-d3ba-49e5-bee7-642eaa370766" />
      <DataType Name="Navy" BaseType="DINT" ArrayType="" Length="" InitialValue="" EnumValue="12" Comment="Navy (Dark blue)" OffsetChannel="" OffsetBit="" IsControllerDefinedType="false" Order="0" OffsetType="" Id="67d9103e-d56f-4c97-9d63-226d6464f8a5" />
      <DataType Name="Purple" BaseType="DINT" ArrayType="" Length="" InitialValue="" EnumValue="13" Comment="Purple (Dark fuchsia)" OffsetChannel="" OffsetBit="" IsControllerDefinedType="false" Order="0" OffsetType="" Id="a13db1c7-5d1c-4ffc-8ab8-32823bb480dc" />
      <DataType Name="SteelBlue" BaseType="DINT" ArrayType="" Length="" InitialValue="" EnumValue="14" Comment="SteelBlue (Dark aqua)" OffsetChannel="" OffsetBit="" IsControllerDefinedType="false" Order="0" OffsetType="" Id="50df37a6-6007-416c-ada2-d14d3e788517" />
      <DataType Name="Gray" BaseType="DINT" ArrayType="" Length="" InitialValue="" EnumValue="15" Comment="Gray (Dark white)" OffsetChannel="" OffsetBit="" IsControllerDefinedType="false" Order="0" OffsetType="" Id="be0952d6-2224-4d74-b112-d835ddda9443" />
      <DataType Name="DimGray" BaseType="DINT" ArrayType="" Length="" InitialValue="" EnumValue="16" Comment="DimGray (Light black)" OffsetChannel="" OffsetBit="" IsControllerDefinedType="false" Order="0" OffsetType="" Id="42bbb257-d219-4fe4-a6dc-6b18524f26ce" />
      <DataType Name="LightCoral" BaseType="DINT" ArrayType="" Length="" InitialValue="" EnumValue="17" Comment="LightCoral (Light red)" OffsetChannel="" OffsetBit="" IsControllerDefinedType="false" Order="0" OffsetType="" Id="ea19a13f-5184-4701-9e38-6debcee735fd" />
      <DataType Name="LightGreen" BaseType="DINT" ArrayType="" Length="" InitialValue="" EnumValue="18" Comment="LightGreen (Light lime)" OffsetChannel="" OffsetBit="" IsControllerDefinedType="false" Order="0" OffsetType="" Id="efa7d2e2-43bd-4d19-95a1-a55d10e710cc" />
      <DataType Name="LightYellow" BaseType="DINT" ArrayType="" Length="" InitialValue="" EnumValue="19" Comment="LightYellow (Light yellow)" OffsetChannel="" OffsetBit="" IsControllerDefinedType="false" Order="0" OffsetType="" Id="f2c2341b-b2bc-4b32-91c5-8407a66e5ec3" />
      <DataType Name="LightBlue" BaseType="DINT" ArrayType="" Length="" InitialValue="" EnumValue="20" Comment="LightBlue (Light blue)" OffsetChannel="" OffsetBit="" IsControllerDefinedType="false" Order="0" OffsetType="" Id="ac5899ce-cfd5-452a-9b50-c48a477a228e" />
      <DataType Name="Plum" BaseType="DINT" ArrayType="" Length="" InitialValue="" EnumValue="21" Comment="Plum (Light fuchsia)" OffsetChannel="" OffsetBit="" IsControllerDefinedType="false" Order="0" OffsetType="" Id="92a6f683-f58c-46d3-a6d8-cfada69dfd1e" />
      <DataType Name="LightSteelBlue" BaseType="DINT" ArrayType="" Length="" InitialValue="" EnumValue="22" Comment="LightSteelBlue (Light aqua)" OffsetChannel="" OffsetBit="" IsControllerDefinedType="false" Order="0" OffsetType="" Id="795512d7-8867-4b3e-b7c6-82b34eb35a6d" />
      <DataType Name="Silver" BaseType="DINT" ArrayType="" Length="" InitialValue="" EnumValue="23" Comment="Silver (Light white)" OffsetChannel="" OffsetBit="" IsControllerDefinedType="false" Order="0" OffsetType="" Id="7034dd7a-6d57-43c6-9ce6-e9da908a7471" />
      <DataType Name="NoUpdate" BaseType="DINT" ArrayType="" Length="" InitialValue="" EnumValue="32" Comment="No update of color" OffsetChannel="" OffsetBit="" IsControllerDefinedType="false" Order="0" OffsetType="" Id="85dea7e2-7aaa-4e8e-a1e7-fd0d42da5036" />
    </DataType>
    <DataType Name="eEffect" BaseType="ENUM" ArrayType="" Length="" InitialValue="" EnumValue="" Comment="Effect selection" OffsetChannel="" OffsetBit="" IsControllerDefinedType="false" Order="0" OffsetType="" Id="f3928296-bd59-445d-89a7-8c899323b261">
      <DataType Name="Off" BaseType="DINT" ArrayType="" Length="" InitialValue="" EnumValue="0" Comment="Turn off" OffsetChannel="" OffsetBit="" IsControllerDefinedType="false" Order="0" OffsetType="" Id="6a8563de-e858-4f5c-b338-f84d51469341" />
      <DataType Name="Steady" BaseType="DINT" ArrayType="" Length="" InitialValue="" EnumValue="1" Comment="Continus" OffsetChannel="" OffsetBit="" IsControllerDefinedType="false" Order="0" OffsetType="" Id="907873c3-3968-4fbe-a2d0-024f63e6ff6a" />
      <DataType Name="Flashing" BaseType="DINT" ArrayType="" Length="" InitialValue="" EnumValue="2" Comment="3 flash" OffsetChannel="" OffsetBit="" IsControllerDefinedType="false" Order="0" OffsetType="" Id="b28f1805-8aac-48d7-8c02-a2969783d7f9" />
      <DataType Name="Blinking" BaseType="DINT" ArrayType="" Length="" InitialValue="" EnumValue="3" Comment="1 Hz" OffsetChannel="" OffsetBit="" IsControllerDefinedType="false" Order="0" OffsetType="" Id="14412f5a-2f29-4925-8298-ffaab966b19a" />
      <DataType Name="FastBlinking" BaseType="DINT" ArrayType="" Length="" InitialValue="" EnumValue="4" Comment="0.5 Hz" OffsetChannel="" OffsetBit="" IsControllerDefinedType="false" Order="0" OffsetType="" Id="98f33eb5-4e31-4485-9ea9-d3d4ecc7cc85" />
      <DataType Name="Rotating" BaseType="DINT" ArrayType="" Length="" InitialValue="" EnumValue="5" Comment="Rotation effect" OffsetChannel="" OffsetBit="" IsControllerDefinedType="false" Order="0" OffsetType="" Id="cb08bd4e-9526-4392-be93-a5c34bb67712" />
      <DataType Name="Level" BaseType="DINT" ArrayType="" Length="" InitialValue="" EnumValue="6" Comment="Level 0-100 %" OffsetChannel="" OffsetBit="" IsControllerDefinedType="false" Order="0" OffsetType="" Id="b8e6043b-97d7-4150-8e47-52751916bfa4" />
    </DataType>
    <DataType Name="eState" BaseType="ENUM" ArrayType="" Length="" InitialValue="" EnumValue="" Comment="" OffsetChannel="" OffsetBit="" IsControllerDefinedType="false" Order="0" OffsetType="" Id="2285d105-5563-4438-a273-69a5e59d10c5">
      <DataType Name="NotStarted" BaseType="DINT" ArrayType="" Length="" InitialValue="" EnumValue="0" Comment="Machine state is not started" OffsetChannel="" OffsetBit="" IsControllerDefinedType="false" Order="0" OffsetType="" Id="bbd41891-3d87-4927-81d4-ff5d51a9854f" />
      <DataType Name="Aborting" BaseType="DINT" ArrayType="" Length="" InitialValue="" EnumValue="1" Comment="The ABORTED state can be entered at any time in response to the Abort command or on the occurrence of a machine fault." OffsetChannel="" OffsetBit="" IsControllerDefinedType="false" Order="0" OffsetType="" Id="b5340f31-b5d2-4466-9427-887837b26605" />
      <DataType Name="Aborted" BaseType="DINT" ArrayType="" Length="" InitialValue="" EnumValue="2" Comment="This state maintains machine status information relevant to the Abort condition. The Stop command will force transition to the Stopped state" OffsetChannel="" OffsetBit="" IsControllerDefinedType="false" Order="0" OffsetType="" Id="3fee931e-6fb1-488b-9fdc-663d35df567d" />
      <DataType Name="Clearing" BaseType="DINT" ArrayType="" Length="" InitialValue="" EnumValue="3" Comment="The procedural element has received a command to clear faults that may have occurred when ABORTING, and are present in the ABORTED state before proceeding to a STOPPED state" OffsetChannel="" OffsetBit="" IsControllerDefinedType="false" Order="0" OffsetType="" Id="88ca2a68-a9c7-49bb-8eba-c2806c709c36" />
      <DataType Name="Stopping" BaseType="DINT" ArrayType="" Length="" InitialValue="" EnumValue="4" Comment="This state executes the logic which brings the machine to a controlled and safe stop" OffsetChannel="" OffsetBit="" IsControllerDefinedType="false" Order="0" OffsetType="" Id="8fc68454-591c-41b3-9841-5ad9a7973579" />
      <DataType Name="Stopped" BaseType="DINT" ArrayType="" Length="" InitialValue="" EnumValue="5" Comment="The machine is powered and stationary.  All communications with other systems are functioning " OffsetChannel="" OffsetBit="" IsControllerDefinedType="false" Order="0" OffsetType="" Id="57151799-1f81-422f-a25f-b7e2ff446a51" />
      <DataType Name="Resetting" BaseType="DINT" ArrayType="" Length="" InitialValue="" EnumValue="6" Comment="This element is the result of a RESET command from the STOPPED state.  RESETTING will typically cause a machine to sound a horn and place the machine in a state where components are energized awaiting a START command" OffsetChannel="" OffsetBit="" IsControllerDefinedType="false" Order="0" OffsetType="" Id="bb0d707b-dd1d-4933-b20c-b3f1b721cff3" />
      <DataType Name="Idle" BaseType="DINT" ArrayType="" Length="" InitialValue="" EnumValue="7" Comment="This is a State which indicates that RESETING is complete.  This state maintains the machine conditions which were achieved during the RESET state." OffsetChannel="" OffsetBit="" IsControllerDefinedType="false" Order="0" OffsetType="" Id="cffabbc0-d676-4c8e-8a1f-3ecacafab8be" />
      <DataType Name="Starting" BaseType="DINT" ArrayType="" Length="" InitialValue="" EnumValue="8" Comment="This state provides the steps needed to start the machine and is a result of a starting type command.  Following this command the machine will begin to “execute”." OffsetChannel="" OffsetBit="" IsControllerDefinedType="false" Order="0" OffsetType="" Id="06363a3d-2b81-456a-98c4-5e51c092712a" />
      <DataType Name="Execute" BaseType="DINT" ArrayType="" Length="" InitialValue="" EnumValue="9" Comment="Once the machine is processing materials it is deemed to be Executing or in the EXECUTE state.  Execute refers to the mode in which the machine is in." OffsetChannel="" OffsetBit="" IsControllerDefinedType="false" Order="0" OffsetType="" Id="1cfe61da-8a32-40ba-bc00-059a395cd20a" />
      <DataType Name="Holding" BaseType="DINT" ArrayType="" Length="" InitialValue="" EnumValue="10" Comment="When the machine is in the EXECUTE state the Hold command can be used to start HOLDING logic which brings the machine to a controlled stop or to a state which represents HELD for the particular machine mode." OffsetChannel="" OffsetBit="" IsControllerDefinedType="false" Order="0" OffsetType="" Id="fba9bd1d-1c84-4951-90b4-133254df8dca" />
      <DataType Name="Held" BaseType="DINT" ArrayType="" Length="" InitialValue="" EnumValue="11" Comment="The HELD state would typically be used by the operator to hold the temporarily hold the machine's operation whilst material blockages are cleared, or to stop throughput whilst a downstream problem is resolved." OffsetChannel="" OffsetBit="" IsControllerDefinedType="false" Order="0" OffsetType="" Id="e272f8ed-7c06-4f7b-a482-4d85ee5e8234" />
      <DataType Name="Unholding" BaseType="DINT" ArrayType="" Length="" InitialValue="" EnumValue="12" Comment="The UNHOLDING state is typically a response to an operator command to resume EXECUTE state.  UNHOLDING prepares the machine to re-enter the EXECUTE state." OffsetChannel="" OffsetBit="" IsControllerDefinedType="false" Order="0" OffsetType="" Id="07e4f3ba-3a77-427e-a192-8713ec3e1429" />
      <DataType Name="Suspending" BaseType="DINT" ArrayType="" Length="" InitialValue="" EnumValue="13" Comment="This state is a result of a command change from the EXECUTE state.  This state is typically required prior to the SUSPENDED wait state, and prepares the machine (ie stops glue cycles, stops carton feeds, etc) prior to the SUSPEND state." OffsetChannel="" OffsetBit="" IsControllerDefinedType="false" Order="0" OffsetType="" Id="e79d3478-789e-4d6a-9bca-d8a27414cacc" />
      <DataType Name="Suspended" BaseType="DINT" ArrayType="" Length="" InitialValue="" EnumValue="14" Comment="The machine may be running at the relevant setpoint speed, there is no product being produced. This state can be reached as a result of a machine status, and differs from HELD in that HELD is typically a result of an operator request" OffsetChannel="" OffsetBit="" IsControllerDefinedType="false" Order="0" OffsetType="" Id="5c3dade3-eab1-4542-b086-5d6f4487d675" />
      <DataType Name="Unsuspending" BaseType="DINT" ArrayType="" Length="" InitialValue="" EnumValue="15" Comment="This state is a result of a request from SUSPENDED state to go back to the EXECUTE state. This state is done prior to EXECUTE state, and prepares the machine for the EXECUTE state." OffsetChannel="" OffsetBit="" IsControllerDefinedType="false" Order="0" OffsetType="" Id="848ba6bb-c6f0-4c59-9c4c-bc92e76fa943" />
      <DataType Name="Completing" BaseType="DINT" ArrayType="" Length="" InitialValue="" EnumValue="16" Comment="When the machine is in the EXECUTE state the Complete command can be used to start COMPLETED logic which brings the machine to a controlled stop" OffsetChannel="" OffsetBit="" IsControllerDefinedType="false" Order="0" OffsetType="" Id="89072517-1d24-40eb-b764-c86f5b464ca5" />
      <DataType Name="Completed" BaseType="DINT" ArrayType="" Length="" InitialValue="" EnumValue="17" Comment="The machine has finished the COMPLETING state and is now waiting for a STOP command that will cause a transition to the STOPPED state" OffsetChannel="" OffsetBit="" IsControllerDefinedType="false" Order="0" OffsetType="" Id="958a8d11-69e9-4804-bec3-b4428dd1f09b" />
      <DataType Name="ErrorState" BaseType="DINT" ArrayType="" Length="" InitialValue="" EnumValue="20" Comment="Machine state in error" OffsetChannel="" OffsetBit="" IsControllerDefinedType="false" Order="0" OffsetType="" Id="f24e3497-aba8-473e-9abf-999309931e5a" />
    </DataType>
    <DataType Name="STATE" BaseType="STRUCT" ArrayType="" Length="" InitialValue="" EnumValue="" Comment="" OffsetChannel="" OffsetBit="" IsControllerDefinedType="false" Order="12" OffsetType="" Id="97be16db-186d-4f2c-a510-6cf40feb9785">
      <DataType Name="Cfg" BaseType="OBJ\State_Config" ArrayType="" Length="" InitialValue="" EnumValue="" Comment="config -" OffsetChannel="" OffsetBit="" IsControllerDefinedType="false" Order="0" OffsetType="" Id="13fd646c-f874-493f-bdc2-521758cc37dc" />
      <DataType Name="Cmd" BaseType="OBJ\State_Command" ArrayType="" Length="" InitialValue="" EnumValue="" Comment="command -" OffsetChannel="" OffsetBit="" IsControllerDefinedType="false" Order="0" OffsetType="" Id="36b1cd12-7ae3-4c02-abcf-66b0349162d3" />
      <DataType Name="SlaveCmd" BaseType="OBJ\State_Command" ArrayType="" Length="" InitialValue="" EnumValue="" Comment="command if slave -" OffsetChannel="" OffsetBit="" IsControllerDefinedType="false" Order="0" OffsetType="" Id="4a05f994-b25c-4e2e-ac33-c95d41570ca7" />
      <DataType Name="Sta" BaseType="OBJ\State_Status" ArrayType="" Length="" InitialValue="" EnumValue="" Comment="status -" OffsetChannel="" OffsetBit="" IsControllerDefinedType="false" Order="0" OffsetType="" Id="7e600bc4-7363-48b3-a016-bba9dd722e39" />
      <DataType Name="Lock" BaseType="OBJ\State_Lock" ArrayType="" Length="" InitialValue="" EnumValue="" Comment="lock -" OffsetChannel="" OffsetBit="" IsControllerDefinedType="false" Order="0" OffsetType="" Id="451247a4-fe1b-4127-abde-ac19c1b5b841" />
      <DataType Name="Value" BaseType="OBJ\eState" ArrayType="" Length="" InitialValue="" EnumValue="" Comment="Current state value" OffsetChannel="" OffsetBit="" IsControllerDefinedType="false" Order="0" OffsetType="" Id="fd79c3ca-6ab3-41c1-bf8b-279bfe603030" />
      <DataType Name="IsClearing" BaseType="Boolean" ArrayType="" Length="" InitialValue="" EnumValue="" Comment="Acting state between ABORTED → STOPPED" OffsetChannel="" OffsetBit="" IsControllerDefinedType="false" Order="0" OffsetType="" Id="f99aa131-5a23-42ab-9c16-e927d9b6c13d" />
      <DataType Name="IsStopped" BaseType="Boolean" ArrayType="" Length="" InitialValue="" EnumValue="" Comment="Waiting state STOPPED" OffsetChannel="" OffsetBit="" IsControllerDefinedType="false" Order="0" OffsetType="" Id="3b8fba7e-9be5-4336-b08d-fc52da403f4f" />
      <DataType Name="IsStarting" BaseType="Boolean" ArrayType="" Length="" InitialValue="" EnumValue="" Comment="Acting state between IDLE → EXECUTE" OffsetChannel="" OffsetBit="" IsControllerDefinedType="false" Order="0" OffsetType="" Id="86231086-1ffe-4aae-8d46-73fa79cd167b" />
      <DataType Name="IsIdle" BaseType="Boolean" ArrayType="" Length="" InitialValue="" EnumValue="" Comment="Waiting state IDLE" OffsetChannel="" OffsetBit="" IsControllerDefinedType="false" Order="0" OffsetType="" Id="de2b6c1f-63a5-4182-99b8-955590c788c1" />
      <DataType Name="IsSuspended" BaseType="Boolean" ArrayType="" Length="" InitialValue="" EnumValue="" Comment="Waiting state SUSPENDED" OffsetChannel="" OffsetBit="" IsControllerDefinedType="false" Order="0" OffsetType="" Id="76088cf5-b5a6-4342-af58-4e6cb0ad0cfd" />
      <DataType Name="IsExecute" BaseType="Boolean" ArrayType="" Length="" InitialValue="" EnumValue="" Comment="Acting state EXECUTE" OffsetChannel="" OffsetBit="" IsControllerDefinedType="false" Order="0" OffsetType="" Id="a4555232-7e48-46b8-83bb-c29c0d11fedc" />
      <DataType Name="IsStopping" BaseType="Boolean" ArrayType="" Length="" InitialValue="" EnumValue="" Comment="Acting state between &quot;Ready&quot; → STOPPED" OffsetChannel="" OffsetBit="" IsControllerDefinedType="false" Order="0" OffsetType="" Id="1d71fa83-ed72-4cd4-ae8c-d901374986c8" />
      <DataType Name="IsAborting" BaseType="Boolean" ArrayType="" Length="" InitialValue="" EnumValue="" Comment="Acting state between &quot;Work&quot; → ABORTED" OffsetChannel="" OffsetBit="" IsControllerDefinedType="false" Order="0" OffsetType="" Id="d50676de-06e6-43ec-814d-4595cee332f4" />
      <DataType Name="IsAborted" BaseType="Boolean" ArrayType="" Length="" InitialValue="" EnumValue="" Comment="Acting state ABORTED" OffsetChannel="" OffsetBit="" IsControllerDefinedType="false" Order="0" OffsetType="" Id="7177dee4-8830-4d2a-8429-191be0a0db2a" />
      <DataType Name="IsHolding" BaseType="Boolean" ArrayType="" Length="" InitialValue="" EnumValue="" Comment="Acting state between EXECUTE → HELD" OffsetChannel="" OffsetBit="" IsControllerDefinedType="false" Order="0" OffsetType="" Id="1918cd48-b689-4236-927d-ce48ded827cd" />
      <DataType Name="IsHeld" BaseType="Boolean" ArrayType="" Length="" InitialValue="" EnumValue="" Comment="Acting state HELD" OffsetChannel="" OffsetBit="" IsControllerDefinedType="false" Order="0" OffsetType="" Id="76b84f09-5074-4a35-986a-9d6bf00b146b" />
      <DataType Name="IsUnHolding" BaseType="Boolean" ArrayType="" Length="" InitialValue="" EnumValue="" Comment="Acting state between HELD → EXECUTE" OffsetChannel="" OffsetBit="" IsControllerDefinedType="false" Order="0" OffsetType="" Id="001a5b4f-b6c8-42af-9a42-9480cd5b5e36" />
      <DataType Name="IsSuspending" BaseType="Boolean" ArrayType="" Length="" InitialValue="" EnumValue="" Comment="Acting state between EXECUTE → SUSPENDED" OffsetChannel="" OffsetBit="" IsControllerDefinedType="false" Order="0" OffsetType="" Id="b25a5e3e-9707-41d1-bd57-df1e018f30c1" />
      <DataType Name="IsUnSuspending" BaseType="Boolean" ArrayType="" Length="" InitialValue="" EnumValue="" Comment="Acting state between SUSPENDED → EXECUTE" OffsetChannel="" OffsetBit="" IsControllerDefinedType="false" Order="0" OffsetType="" Id="5f560581-5006-4611-813d-f37b539b03c9" />
      <DataType Name="IsResetting" BaseType="Boolean" ArrayType="" Length="" InitialValue="" EnumValue="" Comment="Acting state between STOPPED → IDLE" OffsetChannel="" OffsetBit="" IsControllerDefinedType="false" Order="0" OffsetType="" Id="bf3025ee-38f6-4d81-b0aa-2f79e11fb901" />
      <DataType Name="IsCompleting" BaseType="Boolean" ArrayType="" Length="" InitialValue="" EnumValue="" Comment="Acting state between EXECUTE → COMPLETED" OffsetChannel="" OffsetBit="" IsControllerDefinedType="false" Order="0" OffsetType="" Id="7a002306-3c2c-4880-863e-568a755b1acf" />
      <DataType Name="IsCompleted" BaseType="Boolean" ArrayType="" Length="" InitialValue="" EnumValue="" Comment="Acting state COMPLETED" OffsetChannel="" OffsetBit="" IsControllerDefinedType="false" Order="0" OffsetType="" Id="1e20f20d-78e6-4e73-9c74-893f86143bc2" />
    </DataType>
    <DataType Name="State_Config" BaseType="STRUCT" ArrayType="" Length="" InitialValue="" EnumValue="" Comment="" OffsetChannel="" OffsetBit="" IsControllerDefinedType="false" Order="3" OffsetType="" Id="aaf400c2-afd3-444a-af47-0a8b9dee119d">
      <DataType Name="Used_Resetting" BaseType="Boolean" ArrayType="" Length="" InitialValue="" EnumValue="" Comment="State RESETTING is used" OffsetChannel="" OffsetBit="" IsControllerDefinedType="false" Order="0" OffsetType="" Id="5ea300ac-defe-4955-8c9d-ad1115ff808d" />
      <DataType Name="Used_Starting" BaseType="Boolean" ArrayType="" Length="" InitialValue="" EnumValue="" Comment="State STARTING is used" OffsetChannel="" OffsetBit="" IsControllerDefinedType="false" Order="0" OffsetType="" Id="3213c0d1-fc75-45dc-a597-fa8a62f465c5" />
      <DataType Name="Used_Holding" BaseType="Boolean" ArrayType="" Length="" InitialValue="" EnumValue="" Comment="State HOLDING is used" OffsetChannel="" OffsetBit="" IsControllerDefinedType="false" Order="0" OffsetType="" Id="692b673c-e396-4fbe-938b-61f67a60f310" />
      <DataType Name="Used_Held" BaseType="Boolean" ArrayType="" Length="" InitialValue="" EnumValue="" Comment="State HELD is used" OffsetChannel="" OffsetBit="" IsControllerDefinedType="false" Order="0" OffsetType="" Id="37a84fa3-d13f-4eed-b9b3-bba352d4fa3f" />
      <DataType Name="Used_UnHolding" BaseType="Boolean" ArrayType="" Length="" InitialValue="" EnumValue="" Comment="State UNHOLDING is used" OffsetChannel="" OffsetBit="" IsControllerDefinedType="false" Order="0" OffsetType="" Id="aec30230-00e2-4894-a86b-1fc529fc58ae" />
      <DataType Name="Used_Suspending" BaseType="Boolean" ArrayType="" Length="" InitialValue="" EnumValue="" Comment="State SUSPENDING is used" OffsetChannel="" OffsetBit="" IsControllerDefinedType="false" Order="0" OffsetType="" Id="208d88c5-b31c-4ce4-a84a-a37042ccf3e7" />
      <DataType Name="Used_Suspended" BaseType="Boolean" ArrayType="" Length="" InitialValue="" EnumValue="" Comment="State SUSPENDED is used" OffsetChannel="" OffsetBit="" IsControllerDefinedType="false" Order="0" OffsetType="" Id="45a30346-fe46-43ea-b95e-a94cc13a47af" />
      <DataType Name="Used_UnSuspending" BaseType="Boolean" ArrayType="" Length="" InitialValue="" EnumValue="" Comment="State UNSUSPENDED  is used" OffsetChannel="" OffsetBit="" IsControllerDefinedType="false" Order="0" OffsetType="" Id="405712ee-e307-42ea-b4c7-c0f73d5c0c3a" />
      <DataType Name="Used_Aborting" BaseType="Boolean" ArrayType="" Length="" InitialValue="" EnumValue="" Comment="State ABORTING is used" OffsetChannel="" OffsetBit="" IsControllerDefinedType="false" Order="0" OffsetType="" Id="bd52ecbe-4add-4c5d-8f71-70aa6de30e7b" />
      <DataType Name="Used_Clearing" BaseType="Boolean" ArrayType="" Length="" InitialValue="" EnumValue="" Comment="State CLEARING is used" OffsetChannel="" OffsetBit="" IsControllerDefinedType="false" Order="0" OffsetType="" Id="65928ffa-3432-4176-8e31-ca37f2788e74" />
      <DataType Name="Used_Stopping" BaseType="Boolean" ArrayType="" Length="" InitialValue="" EnumValue="" Comment="State STOPPING is used" OffsetChannel="" OffsetBit="" IsControllerDefinedType="false" Order="0" OffsetType="" Id="62e6e90a-9102-4530-843d-c1e4d7e94597" />
      <DataType Name="Used_Completing" BaseType="Boolean" ArrayType="" Length="" InitialValue="" EnumValue="" Comment="State COMPLETING is used" OffsetChannel="" OffsetBit="" IsControllerDefinedType="false" Order="0" OffsetType="" Id="94d3b5d1-2cda-468c-84f6-184f0523e600" />
      <DataType Name="Used_Completed" BaseType="Boolean" ArrayType="" Length="" InitialValue="" EnumValue="" Comment="State COMPLETED is used" OffsetChannel="" OffsetBit="" IsControllerDefinedType="false" Order="0" OffsetType="" Id="05a6804a-161f-4f2f-bf4e-cb9fbe03db00" />
      <DataType Name="Opt_SuspendToHeld" BaseType="Boolean" ArrayType="" Length="" InitialValue="" EnumValue="" Comment="State can move from &quot;Suspend&quot; to &quot;Held&quot;" OffsetChannel="" OffsetBit="" IsControllerDefinedType="false" Order="0" OffsetType="" Id="544b9ac8-a277-4d6d-a2ce-b20e25b819e5" />
      <DataType Name="IsSlave" BaseType="Boolean" ArrayType="" Length="" InitialValue="" EnumValue="" Comment="Machine state is a slave" OffsetChannel="" OffsetBit="" IsControllerDefinedType="false" Order="0" OffsetType="" Id="c845cb18-9fbd-4e3a-8e35-3138c3abcf54" />
    </DataType>
    <DataType Name="State_Command" BaseType="STRUCT" ArrayType="" Length="" InitialValue="" EnumValue="" Comment="" OffsetChannel="" OffsetBit="" IsControllerDefinedType="false" Order="2" OffsetType="" Id="3b505f04-967a-4298-8f3f-bd01b398e8c2">
      <DataType Name="Reset" BaseType="Boolean" ArrayType="" Length="" InitialValue="" EnumValue="" Comment="Order to change state from STOPPED to IDLE" OffsetChannel="" OffsetBit="" IsControllerDefinedType="false" Order="0" OffsetType="" Id="354a3faa-6ade-4737-90b4-656188cf61e9" />
      <DataType Name="Start" BaseType="Boolean" ArrayType="" Length="" InitialValue="" EnumValue="" Comment="Order to change state from IDLE to EXECUTE" OffsetChannel="" OffsetBit="" IsControllerDefinedType="false" Order="0" OffsetType="" Id="04b265bd-1fce-4f2f-b68f-7f38f6b2b7d2" />
      <DataType Name="Stop" BaseType="Boolean" ArrayType="" Length="" InitialValue="" EnumValue="" Comment="Order to change state to STOPPED " OffsetChannel="" OffsetBit="" IsControllerDefinedType="false" Order="0" OffsetType="" Id="e5a7db0a-2043-45f4-a212-a8acb757cfff" />
      <DataType Name="Hold" BaseType="Boolean" ArrayType="" Length="" InitialValue="" EnumValue="" Comment="Order to change state from EXECUTE to HELD" OffsetChannel="" OffsetBit="" IsControllerDefinedType="false" Order="0" OffsetType="" Id="db5ca34d-72b9-4f31-8465-67e6c13d5183" />
      <DataType Name="UnHold" BaseType="Boolean" ArrayType="" Length="" InitialValue="" EnumValue="" Comment="Order to change state from HELD to EXECUTE" OffsetChannel="" OffsetBit="" IsControllerDefinedType="false" Order="0" OffsetType="" Id="341a4166-06ef-4510-ba34-0ab428c0a2f5" />
      <DataType Name="Suspend" BaseType="Boolean" ArrayType="" Length="" InitialValue="" EnumValue="" Comment="Order to change state from EXECUTE to SUSPENDED" OffsetChannel="" OffsetBit="" IsControllerDefinedType="false" Order="0" OffsetType="" Id="026b7f83-958b-4cc8-b500-b256ca90d3ea" />
      <DataType Name="UnSuspend" BaseType="Boolean" ArrayType="" Length="" InitialValue="" EnumValue="" Comment="Order to change state from SUSPENDED to EXECUTE" OffsetChannel="" OffsetBit="" IsControllerDefinedType="false" Order="0" OffsetType="" Id="460e6f55-ef2f-48e3-ae24-059b4ac1d76a" />
      <DataType Name="Complete" BaseType="Boolean" ArrayType="" Length="" InitialValue="" EnumValue="" Comment="Order to change state from EXECUTE to COMPLETED" OffsetChannel="" OffsetBit="" IsControllerDefinedType="false" Order="0" OffsetType="" Id="51858d26-fcdc-4878-ae0d-1a0e73bee170" />
      <DataType Name="Abort" BaseType="Boolean" ArrayType="" Length="" InitialValue="" EnumValue="" Comment="Order to change state to ABORTED" OffsetChannel="" OffsetBit="" IsControllerDefinedType="false" Order="0" OffsetType="" Id="2fc40db1-4882-4ad5-a9ca-e2f191a3078d" />
      <DataType Name="Clear" BaseType="Boolean" ArrayType="" Length="" InitialValue="" EnumValue="" Comment="Order to change state from ABORTED to STOPPED" OffsetChannel="" OffsetBit="" IsControllerDefinedType="false" Order="0" OffsetType="" Id="d11e1d20-dac2-4d68-8fcb-0d226f564df5" />
      <DataType Name="SC" BaseType="Boolean" ArrayType="" Length="" InitialValue="" EnumValue="" Comment="State complete order" OffsetChannel="" OffsetBit="" IsControllerDefinedType="false" Order="0" OffsetType="" Id="63458672-3e7e-4bc2-8627-65405ea97d64" />
      <DataType Name="SC_From" BaseType="OBJ\eState" ArrayType="" Length="" InitialValue="" EnumValue="" Comment="Change of which states" OffsetChannel="" OffsetBit="" IsControllerDefinedType="false" Order="0" OffsetType="" Id="9975c2ec-8143-4b0d-87f4-c13eb96d6a27" />
    </DataType>
    <DataType Name="State_Status" BaseType="STRUCT" ArrayType="" Length="" InitialValue="" EnumValue="" Comment="" OffsetChannel="" OffsetBit="" IsControllerDefinedType="false" Order="1" OffsetType="" Id="af1af615-0e6d-46d3-979a-5b09588f9f23">
      <DataType Name="Work" BaseType="Boolean" ArrayType="" Length="" InitialValue="" EnumValue="" Comment="After Abort" OffsetChannel="" OffsetBit="" IsControllerDefinedType="false" Order="0" OffsetType="" Id="c02f1cff-fff6-4b96-9df7-ed5348a7d58d" />
      <DataType Name="Ready" BaseType="Boolean" ArrayType="" Length="" InitialValue="" EnumValue="" Comment="After Stop" OffsetChannel="" OffsetBit="" IsControllerDefinedType="false" Order="0" OffsetType="" Id="90ff7b3f-23d5-4970-a791-54cef2a8de49" />
      <DataType Name="Run" BaseType="Boolean" ArrayType="" Length="" InitialValue="" EnumValue="" Comment="After Idle" OffsetChannel="" OffsetBit="" IsControllerDefinedType="false" Order="0" OffsetType="" Id="5d622b7f-3b50-4448-93bc-6f3b1a4f5b24" />
    </DataType>
    <DataType Name="State_Lock" BaseType="STRUCT" ArrayType="" Length="" InitialValue="" EnumValue="" Comment="" OffsetChannel="" OffsetBit="" IsControllerDefinedType="false" Order="0" OffsetType="" Id="4178322f-d235-4f2f-972f-1dbb5f7168e1">
      <DataType Name="Aborting" BaseType="Boolean" ArrayType="" Length="" InitialValue="" EnumValue="" Comment="Lock master &quot;Aborting&quot; state" OffsetChannel="" OffsetBit="" IsControllerDefinedType="false" Order="0" OffsetType="" Id="d7a6679f-a99c-4676-bd71-fc591af9ea94" />
      <DataType Name="Clearing" BaseType="Boolean" ArrayType="" Length="" InitialValue="" EnumValue="" Comment="Lock master &quot;Clearing&quot; state" OffsetChannel="" OffsetBit="" IsControllerDefinedType="false" Order="0" OffsetType="" Id="6f190990-3ad8-4ea6-b661-46365bb285cf" />
      <DataType Name="Resetting" BaseType="Boolean" ArrayType="" Length="" InitialValue="" EnumValue="" Comment="Lock master &quot;Resetting&quot; state" OffsetChannel="" OffsetBit="" IsControllerDefinedType="false" Order="0" OffsetType="" Id="cd649b5f-ac80-4825-8739-3e494156abc6" />
      <DataType Name="Starting" BaseType="Boolean" ArrayType="" Length="" InitialValue="" EnumValue="" Comment="Lock master &quot;Starting&quot; state" OffsetChannel="" OffsetBit="" IsControllerDefinedType="false" Order="0" OffsetType="" Id="31c0866a-8694-4215-adeb-a2a926ab7cd7" />
      <DataType Name="Stopping" BaseType="Boolean" ArrayType="" Length="" InitialValue="" EnumValue="" Comment="Lock master &quot;Stopping&quot; state" OffsetChannel="" OffsetBit="" IsControllerDefinedType="false" Order="0" OffsetType="" Id="26a39143-8a7f-44eb-a89f-39dfa5b761a6" />
      <DataType Name="Holding" BaseType="Boolean" ArrayType="" Length="" InitialValue="" EnumValue="" Comment="Lock master &quot;Holding&quot; state" OffsetChannel="" OffsetBit="" IsControllerDefinedType="false" Order="0" OffsetType="" Id="51ffb49a-b570-4c6a-b46f-d04551cb3a8f" />
      <DataType Name="UnHolding" BaseType="Boolean" ArrayType="" Length="" InitialValue="" EnumValue="" Comment="Lock master &quot;UnHolding&quot; state" OffsetChannel="" OffsetBit="" IsControllerDefinedType="false" Order="0" OffsetType="" Id="66230c45-2f37-4657-a2d5-4cd6b7fb7518" />
      <DataType Name="Suspending" BaseType="Boolean" ArrayType="" Length="" InitialValue="" EnumValue="" Comment="Lock master &quot;Suspending&quot; state" OffsetChannel="" OffsetBit="" IsControllerDefinedType="false" Order="0" OffsetType="" Id="dee59eea-aac6-4bbc-af65-0918ce2e7434" />
      <DataType Name="UnSuspending" BaseType="Boolean" ArrayType="" Length="" InitialValue="" EnumValue="" Comment="Lock master &quot;UnSuspending&quot; state" OffsetChannel="" OffsetBit="" IsControllerDefinedType="false" Order="0" OffsetType="" Id="901b0f95-e248-4273-ac6b-14836ecd7adb" />
      <DataType Name="Completing" BaseType="Boolean" ArrayType="" Length="" InitialValue="" EnumValue="" Comment="Lock master &quot;Completing&quot; state" OffsetChannel="" OffsetBit="" IsControllerDefinedType="false" Order="0" OffsetType="" Id="22a8c8f8-0406-4563-b5fc-bc9af8b82aa8" />
    </DataType>
  </DataType>
</data>